neo_core/__init__.py
neo_core/cli.py
neo_core/config.py
neo_core/py.typed
neo_core/database/__init__.py
neo_core/database/base.py
neo_core/database/manager.py
neo_core/database/mixins.py
neo_core/database/session.py
neo_core/models/__init__.py
neo_core/models/application.py
neo_core/models/audit.py
neo_core/models/file.py
neo_core/models/notification.py
neo_core/models/permission.py
neo_core/models/role.py
neo_core/models/session.py
neo_core/models/user.py
neo_core/services/__init__.py
neo_core/services/application.py
neo_core/services/audit.py
neo_core/services/auth.py
neo_core/services/base.py
neo_core/services/cache.py
neo_core/services/crud.py
neo_core/services/email.py
neo_core/services/file.py
neo_core/services/monitoring.py
neo_core/services/notification.py
neo_core/services/role.py
neo_core/services/security.py
neo_core/services/session.py
neo_core/services/user.py
neo_core_fastapi-0.1.0.dist-info/licenses/LICENSE
neo_core_fastapi-0.1.0.dist-info/METADATA
neo_core_fastapi-0.1.0.dist-info/WHEEL
neo_core_fastapi-0.1.0.dist-info/top_level.txt
neo_core_fastapi-0.1.0.dist-info/RECORD
