Metadata-Version: 2.4
Name: neo-core-fastapi
Version: 0.1.0
Summary: Core library for FastAPI dynamic module loader with shared models, services, and utilities
Home-page: https://github.com/neo-core/neo-core-fastapi
Author: Neo Core Team
Author-email: Neo Core Team <dev@neo-core.com>
Maintainer-email: Neo Core Team <dev@neo-core.com>
License: MIT
Project-URL: Homepage, https://github.com/neo-core/neo-core-fastapi
Project-URL: Documentation, https://neo-core-fastapi.readthedocs.io/
Project-URL: Repository, https://github.com/neo-core/neo-core-fastapi.git
Project-URL: Bug Tracker, https://github.com/neo-core/neo-core-fastapi/issues
Project-URL: Changelog, https://github.com/neo-core/neo-core-fastapi/blob/main/CHANGELOG.md
Keywords: fastapi,core,models,services,utilities,database
Classifier: Development Status :: 3 - Alpha
Classifier: Intended Audience :: Developers
Classifier: License :: OSI Approved :: MIT License
Classifier: Operating System :: OS Independent
Classifier: Programming Language :: Python :: 3
Classifier: Programming Language :: Python :: 3.8
Classifier: Programming Language :: Python :: 3.9
Classifier: Programming Language :: Python :: 3.10
Classifier: Programming Language :: Python :: 3.11
Classifier: Framework :: FastAPI
Classifier: Topic :: Internet :: WWW/HTTP :: HTTP Servers
Classifier: Topic :: Software Development :: Libraries :: Python Modules
Requires-Python: >=3.8
License-File: LICENSE
Requires-Dist: fastapi>=0.104.0
Requires-Dist: uvicorn[standard]>=0.24.0
Requires-Dist: pydantic>=2.5.0
Requires-Dist: pydantic-settings>=2.1.0
Requires-Dist: sqlalchemy>=2.0.0
Requires-Dist: alembic>=1.13.0
Requires-Dist: psycopg2-binary>=2.9.0
Requires-Dist: aiosqlite>=0.19.0
Requires-Dist: passlib[bcrypt]>=1.7.4
Requires-Dist: python-jose[cryptography]>=3.3.0
Requires-Dist: python-multipart>=0.0.6
Requires-Dist: cryptography>=41.0.0
Requires-Dist: redis>=5.0.0
Requires-Dist: hiredis>=2.2.0
Requires-Dist: aiosmtplib>=3.0.0
Requires-Dist: email-validator>=2.1.0
Requires-Dist: jinja2>=3.1.0
Requires-Dist: aiofiles>=23.2.0
Requires-Dist: pillow>=10.1.0
Requires-Dist: python-magic>=0.4.27
Requires-Dist: prometheus-client>=0.19.0
Requires-Dist: psutil>=5.9.0
Requires-Dist: httpx>=0.25.0
Requires-Dist: python-dateutil>=2.8.0
Requires-Dist: typing-extensions>=4.8.0
Provides-Extra: dev
Requires-Dist: pytest>=7.4.0; extra == "dev"
Requires-Dist: pytest-asyncio>=0.21.0; extra == "dev"
Requires-Dist: pytest-cov>=4.1.0; extra == "dev"
Requires-Dist: black>=23.7.0; extra == "dev"
Requires-Dist: isort>=5.12.0; extra == "dev"
Requires-Dist: flake8>=6.0.0; extra == "dev"
Requires-Dist: mypy>=1.5.0; extra == "dev"
Requires-Dist: pre-commit>=3.3.0; extra == "dev"
Provides-Extra: testing
Requires-Dist: pytest>=7.4.0; extra == "testing"
Requires-Dist: pytest-asyncio>=0.21.0; extra == "testing"
Requires-Dist: pytest-cov>=4.1.0; extra == "testing"
Requires-Dist: httpx>=0.24.0; extra == "testing"
Requires-Dist: factory-boy>=3.3.0; extra == "testing"
Provides-Extra: docs
Requires-Dist: mkdocs>=1.5.0; extra == "docs"
Requires-Dist: mkdocs-material>=9.1.0; extra == "docs"
Requires-Dist: mkdocstrings[python]>=0.22.0; extra == "docs"
Dynamic: author
Dynamic: home-page
Dynamic: license-file
Dynamic: requires-python
